AUTHORS
CODE_OF_CONDUCT.md
CONTRIBUTING.md
CONTRIBUTORS
LICENSE
MANIFEST.in
README.rst
VERSION
requirements.txt
setup.py
src/logging_gelf/__init__.py
src/logging_gelf/configparser_patch.py
src/logging_gelf/formatters.py
src/logging_gelf/handlers.py
src/logging_gelf/schemas.py
src/logging_gelf.egg-info/PKG-INFO
src/logging_gelf.egg-info/SOURCES.txt
src/logging_gelf.egg-info/dependency_links.txt
src/logging_gelf.egg-info/requires.txt
src/logging_gelf.egg-info/top_level.txt
src/logging_gelf.egg-info/zip-safe
tests/test.py