Metadata-Version: 2.1
Name: logging-gelf
Version: 0.0.30
Summary: Logging bundle to send logs using GELF
Home-page: https://github.com/ovh/python-logging-gelf
Author: OVH SAS
Author-email: github@ovh.net
License: BSD
Classifier: Programming Language :: Python
License-File: LICENSE
License-File: AUTHORS
